pytaskmanager/VERSION
pytaskmanager/__init__.py
pytaskmanager/constants.py
pytaskmanager/utest.py
pytaskmanager/_data/dev/fixtures.yaml
pytaskmanager/_data/dev/node_a.yaml
pytaskmanager/_data/dev/node_b.yaml
pytaskmanager/_data/dev/server.yaml
pytaskmanager/node/DockerManager.py
pytaskmanager/node/FlaskIO.py
pytaskmanager/node/__init__.py
pytaskmanager/node/cli/__init__.py
pytaskmanager/node/cli/node.py
pytaskmanager/server/__init__.py
pytaskmanager/server/db.py
pytaskmanager/server/server.wsgi
pytaskmanager/server/shell.py
pytaskmanager/server/websockets.py
pytaskmanager/server/cli/__init__.py
pytaskmanager/server/cli/server.py
pytaskmanager/server/controllers/__init__.py
pytaskmanager/server/controllers/fixture.py
pytaskmanager/server/resource/__init__.py
pytaskmanager/server/resource/_schema.py
pytaskmanager/server/resource/collaboration.py
pytaskmanager/server/resource/node.py
pytaskmanager/server/resource/organization.py
pytaskmanager/server/resource/result.py
pytaskmanager/server/resource/stats.py
pytaskmanager/server/resource/task.py
pytaskmanager/server/resource/token.py
pytaskmanager/server/resource/user.py
pytaskmanager/server/resource/version.py
pytaskmanager/server/resource/websocket_test.py
pytaskmanager/server/resource/swagger/__init__.py
pytaskmanager/server/resource/swagger/delete_collaboration_node.yaml
pytaskmanager/server/resource/swagger/delete_collaboration_organization.yaml
pytaskmanager/server/resource/swagger/delete_collaboration_task.yaml
pytaskmanager/server/resource/swagger/delete_collaboration_with_id.yaml
pytaskmanager/server/resource/swagger/delete_node_with_node_id.yaml
pytaskmanager/server/resource/swagger/delete_task_with_id.yaml
pytaskmanager/server/resource/swagger/delete_user_with_id.yaml
pytaskmanager/server/resource/swagger/get_collaboration_node.yaml
pytaskmanager/server/resource/swagger/get_collaboration_organization.yaml
pytaskmanager/server/resource/swagger/get_collaboration_task.yaml
ppDLI-0.2.5.dist-info/LICENSE
ppDLI-0.2.5.dist-info/METADATA
ppDLI-0.2.5.dist-info/WHEEL
ppDLI-0.2.5.dist-info/entry_points.txt
ppDLI-0.2.5.dist-info/top_level.txt
ppDLI-0.2.5.dist-info/RECORD
