Metadata-Version: 2.1
Name: ppDLI
Version: 0.2.5
Summary: Package and utilities for distributed learning
Home-page: https://github.com/IKNL/ppDLI
License: UNKNOWN
Requires-Dist: appdirs
Requires-Dist: bcrypt
Requires-Dist: click
Requires-Dist: docker
Requires-Dist: eventlet
Requires-Dist: flask
Requires-Dist: flask-cors
Requires-Dist: flask-jwt-extended
Requires-Dist: flask-restful
Requires-Dist: flask-sqlalchemy
Requires-Dist: flask-marshmallow
Requires-Dist: flask-socketio
Requires-Dist: socketIO-client
Requires-Dist: marshmallow
Requires-Dist: marshmallow-sqlalchemy
Requires-Dist: pyyaml
Requires-Dist: psutil
Requires-Dist: psycopg2
Requires-Dist: requests
Requires-Dist: termcolor
Requires-Dist: sqlalchemy
Requires-Dist: iknl-flasgger
Requires-Dist: schema
Requires-Dist: questionary
Requires-Dist: ipython
